abci/__init__.py
abci/protocol.py
abci/samples.py
abci/server.py
abci/types.py
abci/utils.py
abci/abc/__init__.py
abci/abc/app.py
abci/abc/connections.py
abci/abc/handlers.py
abci/proto/google/protobuf/__init__.py
abci/proto/google/protobuf/duration.py
abci/proto/google/protobuf/timestamp.py
abci/proto/tendermint/abci/__init__.py
abci/proto/tendermint/abci/enums.py
abci/proto/tendermint/abci/request.py
abci/proto/tendermint/abci/response.py
abci/proto/tendermint/abci/types.py
abci/proto/tendermint/crypto/__init__.py
abci/proto/tendermint/crypto/keys.py
abci/proto/tendermint/crypto/profs.py
abci/proto/tendermint/types/__init__.py
abci/proto/tendermint/types/enums.py
abci/proto/tendermint/types/params.py
pyABCI-0.1.0.dist-info/METADATA
pyABCI-0.1.0.dist-info/WHEEL
pyABCI-0.1.0.dist-info/top_level.txt
pyABCI-0.1.0.dist-info/RECORD
